OsmRouteScreenLib/__init__.py
OsmRouteScreenLib/methods.py
OsmRouteScreenLib/options.py
OsmRouteScreenLib/startup.py
OsmRouteScreenLib/utils.py
OsmRouteScreenLib-0.0.5.dist-info/LICENSE
OsmRouteScreenLib-0.0.5.dist-info/METADATA
OsmRouteScreenLib-0.0.5.dist-info/WHEEL
OsmRouteScreenLib-0.0.5.dist-info/top_level.txt
OsmRouteScreenLib-0.0.5.dist-info/RECORD
