Metadata-Version: 2.1
Name: OsmRouteScreenLib
Version: 0.0.5
Summary: Open Street Map route screenshot
Home-page: UNKNOWN
Author: Aleksandr Krasnov
Author-email: akrasnov87@gmail.com
License: UNKNOWN
Keywords: osm route screenshot
Platform: UNKNOWN
Classifier: Programming Language :: Python :: 3.10
Classifier: License :: OSI Approved :: MIT License
Classifier: Operating System :: OS Independent
Requires-Python: >=3.10
License-File: LICENSE
Requires-Dist: mercantile
Requires-Dist: pycairo
